.gitignore
LICENSE.txt
MANIFEST.in
README.md
setup.cfg
setup.py
demo/demo.ipynb
demo/test-data.csv
src/st_clustering/__init__.py
src/st_clustering/st_clustering.py
src/st_clustering.egg-info/PKG-INFO
src/st_clustering.egg-info/SOURCES.txt
src/st_clustering.egg-info/dependency_links.txt
src/st_clustering.egg-info/not-zip-safe
src/st_clustering.egg-info/requires.txt
src/st_clustering.egg-info/top_level.txt