Metadata-Version: 2.1
Name: st-clustering
Version: 0.0.4
Summary: Package containing various spatio-temporal clustering algorithms
Home-page: https://github.com/dbvis-ukon/spatio-temporal-clustering
Author: Eren Cakmak, Manuel Plank
Author-email: eren.cakmak@uni-konstanz.de
License: UNKNOWN
Platform: UNKNOWN
Classifier: Development Status :: 4 - Beta
Classifier: Intended Audience :: Science/Research
Classifier: Intended Audience :: Developers
Classifier: License :: OSI Approved :: MIT License
Classifier: Programming Language :: Python
Classifier: Programming Language :: Python :: 3
Classifier: Programming Language :: Python :: 3.5
Classifier: Programming Language :: Python :: 3.6
Classifier: Programming Language :: Python :: 3.7
Classifier: Topic :: Software Development
Classifier: Topic :: Scientific/Engineering
Classifier: Operating System :: Microsoft :: Windows
Classifier: Operating System :: Unix
Classifier: Operating System :: MacOS
Requires-Python: >=3.6
Provides-Extra: testing
